Workbook

Sheet Overview
A1: HD & LOW — US Comp Sales Point Estimates, Q3 FY2026 – Q2 FY2027
A3: Point Estimate = 0.85 x (Recent Performance Baseline + Macro Adjustment) + 0.15 x LIRA's own forward-looking projection. The baseline is each company's trailing 2-quarter average comp sales, anchoring every estimate to real recent momentum. The macro adjustment reflects how far the strongest predictor at that horizon (mortgage rate near-term, consumer sentiment far-out) is expected to move from ITS OWN recent normal -- not extrapolated from a single volatile reading. Consumer sentiment's projection tapers its recent downward drift rather than assuming it continues in a straight line for 5 quarters, and the farthest-out quarter's regression slope is capped to guard against small-sample noise. LIRA (Harvard JCHS) is blended in at a small weight since it's the only series with genuine forward-looking data for our exact forecast quarters, despite a historically weak correlation. Full step-by-step build on the Point Estimates tab.
A6: Company | B6: Fiscal Quarter | C6: Predictor Used | D6: Projected Predictor Value | E6: Point Estimate (US Comp %) | F6: LIRA Projection (15% blend weight)
A7: HD | B7: Q3 FY2026 | C7: Mortgage Rate (Leads 1Q, blended) | D7: ='Point Estimates'!B15 -> 6.4048077 | E7: ='Point Estimates'!B20 -> 0.0079508042 | F7: ='LIRA vs Comp Correlation'!E17 -> 0.021
A8: HD | B8: Q4 FY2026 | C8: Mortgage Rate (Leads 2Q, blended) | D8: ='Point Estimates'!B30 -> 6.4048077 | E8: ='Point Estimates'!B35 -> 0.0090803467 | F8: ='LIRA vs Comp Correlation'!E18 -> 0.021
A9: HD | B9: Q1 FY2027 | C9: Consumer Sentiment (Leads 4Q, tapered) | D9: ='Point Estimates'!B48 -> 49.47864 | E9: ='Point Estimates'!B53 -> 0.0022566165 | F9: ='LIRA vs Comp Correlation'!E19 -> 0.007
A10: HD | B10: Q2 FY2027 | C10: Consumer Sentiment (Leads 5Q, tapered, slope-capped) | D10: ='Point Estimates'!B66 -> 49.011538 | E10: ='Point Estimates'!B73 -> -0.0022061321 | F10: ='LIRA vs Comp Correlation'!E20 -> 0.005
A11: LOW | B11: Q3 FY2026 | C11: Mortgage Rate (Leads 1Q, blended) | D11: ='Point Estimates'!B87 -> 6.4048077 | E11: ='Point Estimates'!B92 -> 0.0048789413 | F11: ='LIRA vs Comp Correlation'!E17 -> 0.021
A12: LOW | B12: Q4 FY2026 | C12: Mortgage Rate (Leads 2Q, blended) | D12: ='Point Estimates'!B102 -> 6.4048077 | E12: ='Point Estimates'!B107 -> 0.0053991214 | F12: ='LIRA vs Comp Correlation'!E18 -> 0.021
A13: LOW | B13: Q1 FY2027 | C13: Consumer Sentiment (Leads 4Q, tapered) | D13: ='Point Estimates'!B120 -> 49.722807 | E13: ='Point Estimates'!B125 -> -0.0021796966 | F13: ='LIRA vs Comp Correlation'!E19 -> 0.007
A14: LOW | B14: Q2 FY2027 | C14: Consumer Sentiment (Leads 5Q, tapered, slope-capped) | D14: ='Point Estimates'!B138 -> 49.253905 | E14: ='Point Estimates'!B145 -> -0.0084615691 | F14: ='LIRA vs Comp Correlation'!E20 -> 0.005
A16: Key Finding: a coherent, moderate deceleration story
A17: After anchoring estimates to each company's recent trailing performance (rather than a pure macro-level regression) and tapering the consumer-sentiment extrapolation, the model now shows modestly positive comp sales in the near term (Q3/Q4 FY2026) fading toward roughly flat to modestly negative by mid-2027 (Q1/Q2 FY2027) -- broadly in line with both companies' FY2026 guidance (flat to +2.0% HD, flat LOW) and LIRA's own projected deceleration, rather than sharply diverging from them as an earlier macro-only version of this model did. The remaining softness in the two farthest-out quarters still reflects a genuine signal: consumer sentiment has been drifting lower for a year, and if that continues even at a decelerating pace, it's a real (if modest) headwind companies' own guidance may be counting on continued execution (market share, Pro-channel growth, pricing) to offset.
A19: FY2026 Guidance Cross-Check
A20: HD | B20: FY2026 total comp sales: flat to +2.0% (reaffirmed 8/18/2026). US comp typically runs slightly below total comp recently (~0.1-0.4 pt gap), so US comp guidance is inferred as roughly flat to +1.7%.
A21: LOW | B21: FY2026 total comp sales: flat (narrowed from flat to +2.0% on 8/19/2026). LOW no longer breaks out US comp separately (divested Canada in FY2022), so total comp guidance applies directly to US comp.
A23: Data sources: US comp sales from HD's/LOW's own quarterly earnings releases. Mortgage rate = Freddie Mac PMMS 30-Yr Fixed weekly average (FRED). Consumer Sentiment = University of Michigan Survey of Consumers (FRED). LIRA = Harvard JCHS, Q2 2026 release. Full source detail and raw series in HD_LOW_Source_Data.xlsx. All public sources. Built 2026-08-20.

Sheet Quarterly Data
A1: HD & LOW — Consolidated Quarterly Data (Comp Sales, Macro Indicators, NAICS444, LIRA)
A2: One row per HD/LOW fiscal quarter. Each company's 30 ACTUAL quarters (Q1 FY2019 - Q2 FY2026) are immediately followed by that SAME company's 4 PROJECTED quarters (Q3 FY2026 - Q2 FY2027, see Period Type column) -- HD rows 5-38, LOW rows 39-72 -- so each company's history reads as one continuous chronological block. Columns E-J (Mortgage Rate through Building Permits) and column K (Data Quality Notes) are sourced from Housing_Macro_Indicators.xlsx's original 'Quarterly Data' tab -- see HD_LOW_Source_Data.xlsx for the raw monthly/weekly readings and day-weighted allocation methodology behind those 6 series (blank for the 4 projected rows -- future macro readings aren't known). Columns L-P (Comp Sales % US, NAICS444, LIRA, Notes, Period Type) are appended after column K. Column L is a hardcoded value (with a source-citing comment) for actual rows, and a LIVE formula linked to the Point Estimates tab for the 4 projected rows per company, so refining the forecast methodology updates these automatically. Built 2026-08-20.
A4: Company | B4: Fiscal Quarter | C4: Quarter Start Date | D4: Quarter End Date | E4: 30-Yr Mortgage Rate (%) | F4: Existing Home Sales (M, SAAR) | G4: New Home Sales (M, SAAR) | H4: CPI-U Y/Y Growth (%) | I4: U. Michigan Consumer Sentiment | J4: Building Permits (M Units, SAAR) | K4: Data Quality Notes | L4: Comp Sales % (US) | M4: NAICS444 Retail Sales Y/Y Growth | N4: LIRA Mapped 4-Qtr YoY Rate of Change | O4: Comp / NAICS444 / LIRA Notes | P4: Period Type
A5: HD | B5: Q1 FY2019 | C5: 43500 | D5: 43590 | E5: 4.25 | F5: 5.292967 | G5: 0.68804608 | H5: 0.017974246 | I5: 96.828571 | J5: 1.3042857 | K5: All series available as full fiscal-quarter averages. | L5: 0.03 | P5: Actual
A6: HD | B6: Q2 FY2019 | C6: 43591 | D6: 43681 | E6: 3.8646154 | F6: 5.3507692 | G6: 0.66898454 | H6: 0.017464619 | I6: 98.413187 | J6: 1.348011 | K6: All series available as full fiscal-quarter averages. | L6: 0.031 | P6: Actual
A7: HD | B7: Q3 FY2019 | C7: 43682 | D7: 43772 | E7: 3.63 | F7: 5.4389011 | G7: 0.71534397 | H7: 0.017523647 | I7: 93.093407 | J7: 1.4934286 | K7: All series available as full fiscal-quarter averages. | L7: 0.038 | P7: Actual
A8: HD | B8: Q4 FY2019 | C8: 43773 | D8: 43863 | E8: 3.6753846 | F8: 5.4614286 | G8: 0.70004951 | H8: 0.022820804 | I8: 98.765934 | J8: 1.4867033 | K8: All series available as full fiscal-quarter averages. | L8: 0.053 | P8: Actual
A9: HD | B9: Q1 FY2020 | C9: 43864 | D9: 43954 | E9: 3.3992308 | F9: 5.0636264 | G9: 0.63634266 | H9: 0.012967844 | I9: 86.373626 | J9: 1.2906703 | K9: All series available as full fiscal-quarter averages. | L9: 0.075 | M9: 0.043498858 | P9: Actual
A10: HD | B10: Q2 FY2020 | C10: 43955 | D10: 44045 | E10: 3.1276923 | F10: 4.8872527 | G10: 0.87110461 | H10: 0.0061011169 | I10: 74.31978 | J10: 1.3823626 | K10: All series available as full fiscal-quarter averages. | L10: 0.25 | M10: 0.17523525 | P10: Actual
A11: HD | B11: Q3 FY2020 | C11: 44046 | D11: 44136 | E11: 2.8823077 | F11: 6.4751648 | G11: 1.0071598 | H11: 0.012793131 | I11: 78.830769 | J11: 1.6005495 | K11: All series available as full fiscal-quarter averages. | L11: 0.246 | M11: 0.16242177 | P11: Actual
A12: HD | B12: Q4 FY2020 | C12: 44137 | D12: 44227 | E12: 2.7246154 | F12: 6.7138462 | G12: 0.883299 | H12: 0.013024825 | I12: 78.90989 | J12: 1.7693297 | K12: All series available as full fiscal-quarter averages. | L12: 0.25 | M12: 0.17564951 | P12: Actual
A13: HD | B13: Q1 FY2021 | C13: 44228 | D13: 44318 | E13: 2.99 | F13: 6.0172527 | G13: 0.81287482 | H13: 0.028953556 | I13: 83.484615 | J13: 1.7234066 | K13: All series available as full fiscal-quarter averages. | L13: 0.299 | M13: 0.28026534 | P13: Actual
A14: HD | B14: Q2 FY2021 | C14: 44319 | D14: 44409 | E14: 2.93 | F14: 5.8853846 | G14: 0.72516632 | H14: 0.052388271 | I14: 83.03956 | J14: 1.6779231 | K14: All series available as full fiscal-quarter averages. | L14: 0.034 | M14: 0.091230187 | P14: Actual
A15: HD | B15: Q3 FY2021 | C15: 44410 | D15: 44500 | E15: 2.9338462 | F15: 6.1718681 | G15: 0.70319032 | H15: 0.056266336 | I15: 71.601099 | J15: 1.696033 | K15: All series available as full fiscal-quarter averages. | L15: 0.055 | M15: 0.080830547 | P15: Actual
A16: HD | B16: Q4 FY2021 | C16: 44501 | D16: 44591 | E16: 3.1953846 | F16: 6.3778022 | G16: 0.80247313 | H16: 0.071021417 | I16: 68.424176 | J16: 1.859956 | K16: All series available as full fiscal-quarter averages. | L16: 0.076 | M16: 0.13202263 | P16: Actual
A17: HD | B17: Q1 FY2022 | C17: 44592 | D17: 44682 | E17: 4.2953846 | F17: 5.7982418 | G17: 0.70078385 | H17: 0.081979221 | I17: 62.432967 | J17: 1.8644066 | K17: All series available as full fiscal-quarter averages. | L17: 0.017 | M17: 0.040642888 | P17: Actual
A18: HD | B18: Q2 FY2022 | C18: 44683 | D18: 44773 | E18: 5.3984615 | F18: 5.11 | G18: 0.57892004 | H18: 0.087007129 | I18: 53.28022 | J18: 1.7145824 | K18: All series available as full fiscal-quarter averages. | L18: 0.054 | M18: 0.066951675 | P18: Actual
A19: HD | B19: Q3 FY2022 | C19: 44774 | D19: 44864 | E19: 6.0807692 | F19: 4.6483516 | G19: 0.59101945 | H19: 0.080579214 | I19: 58.892308 | J19: 1.5778571 | K19: All series available as full fiscal-quarter averages. | L19: 0.045 | M19: 0.10337001 | P19: Actual
A20: HD | B20: Q4 FY2022 | C20: 44865 | D20: 44955 | E20: 6.4715385 | F20: 4.0412088 | G20: 0.61918355 | H20: 0.066503547 | I20: 60.404396 | J20: 1.414978 | K20: All series available as full fiscal-quarter averages. | L20: -0.003 | M20: 0.021008837 | P20: Actual
... A22: HD | B22: Q2 FY2023 | C22: 45047 | D22: 45137 | E22: 6.6638462 | F22: 4.178022 | G22: 0.71708133 | H22: 0.033870243 | I22: 64.835165 | J22: 1.5193297 | K22: All series available as full fiscal-quarter averages. | L22: -0.02 | M22: -0.024479818 | P22: Actual
A23: HD | B23: Q3 FY2023 | C23: 45138 | D23: 45228 | E23: 7.28 | F23: 3.9342857 | G23: 0.6721208 | H23: 0.035289295 | I23: 67.110989 | J23: 1.5505714 | K23: All series available as full fiscal-quarter averages. | L23: -0.035 | M23: -0.041372021 | N23: 0.044 | P23: Actual
A24: HD | B24: Q4 FY2023 | C24: 45229 | D24: 45319 | E24: 7.0030769 | F24: 3.8610989 | G24: 0.64156766 | H24: 0.031937419 | I24: 69.662637 | J24: 1.5199231 | K24: All series available as full fiscal-quarter averages. | L24: -0.04 | M24: -0.043730552 | N24: -0.01 | P24: Actual
A25: HD | B25: Q1 FY2024 | C25: 45320 | D25: 45410 | E25: 6.8561538 | F25: 4.2289011 | G25: 0.67984628 | H25: 0.032994397 | I25: 77.913187 | J25: 1.5025165 | K25: All series available as full fiscal-quarter averages. | L25: -0.032 | M25: -0.029585802 | N25: -0.006 | P25: Actual
A26: HD | B26: Q2 FY2024 | C26: 45411 | D26: 45501 | E26: 6.9507692 | F26: 3.9889011 | G26: 0.69406208 | H26: 0.030400328 | I26: 68.150549 | J26: 1.4371538 | K26: All series available as full fiscal-quarter averages. | L26: -0.036 | M26: -0.017024035 | N26: -0.023 | P26: Actual
A27: HD | B27: Q3 FY2024 | C27: 45502 | D27: 45592 | E27: 6.3569231 | F27: 3.886044 | G27: 0.68162838 | H27: 0.02518361 | I27: 69.347253 | J27: 1.4502308 | K27: All series available as full fiscal-quarter averages. | L27: -0.012 | M27: 0.017002023 | N27: -0.025 | P27: Actual
A28: HD | B28: Q4 FY2024 | C28: 45593 | D28: 45690 | E28: 6.8278571 | F28: 4.1508163 | G28: 0.67605647 | H28: 0.028499916 | I28: 72.266327 | J28: 1.4777755 | K28: All series available as full fiscal-quarter averages. | L28: 0.013 | M28: 0.018947587 | N28: -0.019 | P28: Actual
A29: HD | B29: Q1 FY2025 | C29: 45691 | D29: 45781 | E29: 6.7407692 | F29: 4.0824176 | G29: 0.66515004 | H29: 0.024716838 | I29: 57.406593 | J29: 1.460022 | K29: All series available as full fiscal-quarter averages. | L29: 0.002 | M29: 0.029038745 | N29: -0.001 | P29: Actual
A30: HD | B30: Q2 FY2025 | C30: 45782 | D30: 45872 | E30: 6.7838462 | F30: 3.9892308 | G30: 0.64762009 | H30: 0.025937339 | I30: 58.436264 | J30: 1.4026703 | K30: All series available as full fiscal-quarter averages. | L30: 0.014 | M30: -0.017172492 | N30: 0.012 | P30: Actual
A31: HD | B31: Q3 FY2025 | C31: 45873 | D31: 45963 | E31: 6.3869231 | F31: 4.0567033 | G31: 0.68895358 | H31: 0.028973895 | I31: 55.452747 | J31: 1.4046374 | K31: All series available as full fiscal-quarter averages. | L31: 0.001 | M31: -0.034246323 | N31: 0.016 | P31: Actual
A32: HD | B32: Q4 FY2025 | C32: 45964 | D32: 46054 | E32: 6.1776923 | F32: 4.1295604 | G32: 0.68260227 | H32: 0.025797388 | I32: 53.548352 | J32: 1.4313956 | K32: All series available as full fiscal-quarter averages. | L32: 0.003 | M32: 0.0044184598 | N32: 0.018 | P32: Actual
A33: HD | B33: Q1 FY2026 | C33: 46055 | D33: 46145 | E33: 6.1969231 | F33: 4.0320879 | G33: 0.64475113 | H33: 0.032148644 | I33: 52.845055 | J33: 1.4368462 | K33: All series available as full fiscal-quarter averages. | L33: 0.004 | M33: 0.03792277 | N33: 0.019 | P33: Actual
A34: HD | B34: Q2 FY2026 | C34: 46146 | D34: 46236 | E34: 6.4953846 | H34: 0.036781701 | K34: Quarter extends beyond available source data for one or more series -- left blank; see the respective 'by Fiscal Qtr' tab. | L34: 0.013 | N34: 0.02 | O34: NAICS444 retail-sales Y/Y growth not yet available (Census reporting lag) | P34: Actual
A35: HD | B35: Q3 FY2026 | C35: 46237 | D35: 46327 | K35: Projected quarter -- macro readings not yet known. | L35: ='Point Estimates'!B20 -> 0.0079508042 | N35: 0.021 | O35: PROJECTED -- see Point Estimates tab for regression detail. | P35: Projected
A36: HD | B36: Q4 FY2026 | C36: 46328 | D36: 46418 | K36: Projected quarter -- macro readings not yet known. | L36: ='Point Estimates'!B35 -> 0.0090803467 | N36: 0.021 | O36: PROJECTED -- see Point Estimates tab for regression detail. | P36: Projected
A37: HD | B37: Q1 FY2027 | C37: 46419 | D37: 46509 | K37: Projected quarter -- macro readings not yet known. | L37: ='Point Estimates'!B53 -> 0.0022566165 | N37: 0.007 | O37: PROJECTED -- see Point Estimates tab for regression detail. | P37: Projected
A38: HD | B38: Q2 FY2027 | C38: 46510 | D38: 46600 | K38: Projected quarter -- macro readings not yet known. | L38: ='Point Estimates'!B73 -> -0.0022061321 | N38: 0.005 | O38: PROJECTED -- see Point Estimates tab for regression detail. | P38: Projected
A39: LOW | B39: Q1 FY2019 | C39: 43498 | D39: 43588 | E39: 4.25 | F39: 5.2967033 | G39: 0.68869469 | H39: 0.017915096 | I39: 96.692308 | J39: 1.3029451 | K39: All series available as full fiscal-quarter averages. | L39: 0.042 | P39: Actual
A40: LOW | B40: Q2 FY2019 | C40: 43589 | D40: 43679 | E40: 3.8646154 | F40: 5.3474725 | G40: 0.66692864 | H40: 0.017473497 | I40: 98.637363 | J40: 1.345044 | K40: All series available as full fiscal-quarter averages. | L40: 0.032 | P40: Actual
A41: LOW | B41: Q3 FY2019 | C41: 43680 | D41: 43770 | E41: 3.63 | F41: 5.441978 | G41: 0.71532572 | H41: 0.017457502 | I41: 92.93956 | J41: 1.4922637 | K41: All series available as full fiscal-quarter averages. | L41: 0.03 | P41: Actual
A42: LOW | B42: Q4 FY2019 | C42: 43771 | D42: 43861 | E42: 3.6753846 | F42: 5.4521978 | G42: 0.70016789 | H42: 0.022758348 | I42: 98.673626 | J42: 1.4883297 | K42: All series available as full fiscal-quarter averages. | L42: 0.026 | P42: Actual
A43: LOW | B43: Q1 FY2020 | C43: 43862 | D43: 43952 | E43: 3.3992308 | F43: 5.1045055 | G43: 0.63634311 | H43: 0.013455572 | I43: 87.004396 | J43: 1.2952857 | K43: All series available as full fiscal-quarter averages. | L43: 0.123 | M43: 0.041357524 | P43: Actual
A44: LOW | B44: Q2 FY2020 | C44: 43953 | D44: 44043 | E44: 3.1276923 | F44: 4.8413187 | G44: 0.86432457 | H44: 0.0058391155 | I44: 74.28022 | J44: 1.3761429 | K44: All series available as full fiscal-quarter averages. | L44: 0.351 | M44: 0.17512468 | P44: Actual
A45: LOW | B45: Q3 FY2020 | C45: 44044 | D45: 44134 | E45: 2.8823077 | F45: 6.4582418 | G45: 1.008521 | H45: 0.012816043 | I45: 78.715385 | J45: 1.597956 | K45: All series available as full fiscal-quarter averages. | L45: 0.304 | M45: 0.16101029 | P45: Actual
A46: LOW | B46: Q4 FY2020 | C46: 44135 | D46: 44225 | E46: 2.7246154 | F46: 6.7156044 | G46: 0.8845058 | H46: 0.013043239 | I46: 78.917582 | J46: 1.7648462 | K46: All series available as full fiscal-quarter averages. | L46: 0.286 | M46: 0.17723534 | P46: Actual
A47: LOW | B47: Q1 FY2021 | C47: 44226 | D47: 44316 | E47: 2.99 | F47: 6.0368132 | G47: 0.81687308 | H47: 0.028103869 | I47: 83.398901 | J47: 1.7267253 | K47: All series available as full fiscal-quarter averages. | L47: 0.244 | M47: 0.2818578 | P47: Actual
A48: LOW | B48: Q2 FY2021 | C48: 44317 | D48: 44407 | E48: 2.93 | F48: 5.8824176 | G48: 0.72517579 | H48: 0.052355754 | I48: 83.196703 | J48: 1.677967 | K48: All series available as full fiscal-quarter averages. | L48: -0.022 | M48: 0.091130394 | P48: Actual
A49: LOW | B49: Q3 FY2021 | C49: 44408 | D49: 44498 | E49: 2.9338462 | F49: 6.162967 | G49: 0.70379013 | H49: 0.056022093 | I49: 71.69011 | J49: 1.6961209 | K49: All series available as full fiscal-quarter averages. | L49: 0.026 | M49: 0.081412024 | P49: Actual
A50: LOW | B50: Q4 FY2021 | C50: 44499 | D50: 44589 | E50: 3.1953846 | F50: 6.3742857 | G50: 0.79983447 | H50: 0.070752108 | I50: 68.523077 | J50: 1.855033 | K50: All series available as full fiscal-quarter averages. | L50: 0.051 | M50: 0.13183235 | P50: Actual
A51: LOW | B51: Q1 FY2022 | C51: 44590 | D51: 44680 | E51: 4.2953846 | F51: 5.82 | G51: 0.70482074 | H51: 0.081869941 | I51: 62.551648 | J51: 1.8675495 | K51: All series available as full fiscal-quarter averages. | L51: -0.038 | M51: 0.041325479 | P51: Actual
A52: LOW | B52: Q2 FY2022 | C52: 44681 | D52: 44771 | E52: 5.3984615 | F52: 5.1253846 | G52: 0.5809116 | H52: 0.08691577 | I52: 53.506593 | J52: 1.7161868 | K52: All series available as full fiscal-quarter averages. | L52: 0.002 | M52: 0.066516024 | P52: Actual
A53: LOW | B53: Q3 FY2022 | C53: 44772 | D53: 44862 | E53: 6.0807692 | F53: 4.6567033 | G53: 0.5899042 | H53: 0.08072593 | I53: 58.707692 | J53: 1.5805824 | K53: All series available as full fiscal-quarter averages. | L53: 0.03 | M53: 0.10306265 | P53: Actual
A54: LOW | B54: Q4 FY2022 | C54: 44863 | D54: 44960 | E54: 6.4442857 | F54: 4.0647959 | G54: 0.61960247 | H54: 0.066384353 | I54: 60.684694 | J54: 1.4242857 | K54: All series available as full fiscal-quarter averages. | L54: -0.007 | M54: 0.022257283 | P54: Actual
... A56: LOW | B56: Q2 FY2023 | C56: 45052 | D56: 45142 | E56: 6.7030769 | F56: 4.1640659 | G56: 0.71298389 | H56: 0.033614446 | I56: 65.42967 | J56: 1.5195385 | K56: All series available as full fiscal-quarter averages. | L56: -0.016 | M56: -0.034890347 | P56: Actual
A57: LOW | B57: Q3 FY2023 | C57: 45143 | D57: 45233 | E57: 7.3461538 | F57: 3.9212088 | G57: 0.67092258 | H57: 0.035082764 | I57: 66.697802 | J57: 1.546978 | K57: All series available as full fiscal-quarter averages. | L57: -0.074 | M57: -0.044113213 | N57: 0.044 | P57: Actual
A58: LOW | B58: Q4 FY2023 | C58: 45234 | D58: 45324 | E58: 6.9161538 | F58: 3.88 | G58: 0.64327612 | H58: 0.031827551 | I58: 70.534066 | J58: 1.5220879 | K58: All series available as full fiscal-quarter averages. | L58: -0.062 | M58: -0.046394524 | N58: -0.01 | P58: Actual
A59: LOW | B59: Q1 FY2024 | C59: 45325 | D59: 45415 | E59: 6.9015385 | F59: 4.2272527 | G59: 0.68057188 | H59: 0.033102491 | I59: 77.593407 | J59: 1.4952967 | K59: All series available as full fiscal-quarter averages. | L59: -0.041 | M59: -0.029638372 | N59: -0.006 | P59: Actual
A60: LOW | B60: Q2 FY2024 | C60: 45416 | D60: 45506 | E60: 6.9130769 | F60: 3.9774725 | G60: 0.69570295 | H60: 0.030052731 | I60: 67.857143 | J60: 1.4393626 | K60: All series available as full fiscal-quarter averages. | L60: -0.051 | M60: -0.01369252 | N60: -0.023 | P60: Actual
A61: LOW | B61: Q3 FY2024 | C61: 45507 | D61: 45597 | E61: 6.3561538 | F61: 3.8906593 | G61: 0.67754121 | H61: 0.025261124 | I61: 69.553846 | J61: 1.4493956 | K61: All series available as full fiscal-quarter averages. | L61: -0.011 | M61: 0.020613874 | N61: -0.025 | P61: Actual
A62: LOW | B62: Q4 FY2024 | C62: 45598 | D62: 45688 | E62: 6.8361538 | F62: 4.1568132 | G62: 0.67882188 | H62: 0.028582562 | I62: 72.515385 | J62: 1.479978 | K62: All series available as full fiscal-quarter averages. | L62: 0.002 | M62: 0.013380506 | N62: -0.019 | P62: Actual
A63: LOW | B63: Q1 FY2025 | C63: 45689 | D63: 45779 | E63: 6.7407692 | F63: 4.0874725 | G63: 0.6655676 | H63: 0.024819093 | I63: 57.681319 | J63: 1.4606813 | K63: All series available as full fiscal-quarter averages. | L63: -0.017 | M63: 0.0039649273 | N63: -0.001 | P63: Actual
A64: LOW | B64: Q2 FY2025 | C64: 45780 | D64: 45870 | E64: 6.7838462 | F64: 3.9898901 | G64: 0.64595554 | H64: 0.0258139 | I64: 58.304396 | J64: 1.4041868 | K64: All series available as full fiscal-quarter averages. | L64: 0.011 | M64: -0.0092999129 | N64: 0.012 | P64: Actual
A65: LOW | B65: Q3 FY2025 | C65: 45871 | D65: 45961 | E65: 6.3869231 | F65: 4.0538462 | G65: 0.68764979 | H65: 0.029013715 | I65: 55.610989 | J65: 1.4031648 | K65: All series available as full fiscal-quarter averages. | L65: 0.004 | M65: -0.034501738 | N65: 0.016 | P65: Actual
A66: LOW | B66: Q4 FY2025 | C66: 45962 | D66: 46052 | E66: 6.1776923 | F66: 4.1324176 | G66: 0.68599451 | H66: 0.025921435 | I66: 53.427473 | J66: 1.4302418 | K66: All series available as full fiscal-quarter averages. | L66: 0.013 | M66: 0.0031694516 | N66: 0.018 | P66: Actual
A67: LOW | B67: Q1 FY2026 | C67: 46053 | D67: 46143 | E67: 6.1969231 | F67: 4.0283516 | G67: 0.64442052 | H67: 0.031692183 | I67: 53.102198 | J67: 1.4380879 | K67: All series available as full fiscal-quarter averages. | L67: 0.006 | M67: 0.037752274 | N67: 0.019 | P67: Actual
A68: LOW | B68: Q2 FY2026 | C68: 46144 | D68: 46234 | E68: 6.4953846 | F68: 4.1061538 | H68: 0.037014697 | J68: 1.4093736 | K68: Quarter extends beyond available source data for one or more series -- left blank; see the respective 'by Fiscal Qtr' tab. | L68: 0.002 | N68: 0.02 | O68: NAICS444 retail-sales Y/Y growth not yet available (Census reporting lag) | P68: Actual
A69: LOW | B69: Q3 FY2026 | C69: 46235 | D69: 46325 | K69: Projected quarter -- macro readings not yet known. | L69: ='Point Estimates'!B92 -> 0.0048789413 | N69: 0.021 | O69: PROJECTED -- see Point Estimates tab for regression detail. | P69: Projected
A70: LOW | B70: Q4 FY2026 | C70: 46326 | D70: 46416 | K70: Projected quarter -- macro readings not yet known. | L70: ='Point Estimates'!B107 -> 0.0053991214 | N70: 0.021 | O70: PROJECTED -- see Point Estimates tab for regression detail. | P70: Projected
A71: LOW | B71: Q1 FY2027 | C71: 46417 | D71: 46507 | K71: Projected quarter -- macro readings not yet known. | L71: ='Point Estimates'!B125 -> -0.0021796966 | N71: 0.007 | O71: PROJECTED -- see Point Estimates tab for regression detail. | P71: Projected
A72: LOW | B72: Q2 FY2027 | C72: 46508 | D72: 46598 | K72: Projected quarter -- macro readings not yet known. | L72: ='Point Estimates'!B145 -> -0.0084615691 | N72: 0.005 | O72: PROJECTED -- see Point Estimates tab for regression detail. | P72: Projected
A74: Amber italic rows are PROJECTED quarters (regression point estimates, not company-reported actuals) -- see the Point Estimates tab for full methodology. Quarter start/end dates for projected rows are estimated (standard 13-week cadence from the last known quarter), not confirmed by the company. Amber italic cells within ACTUAL rows flag a specific data gap (see that row's notes).

Sheet LIRA vs Comp Correlation
A1: LIRA (Harvard JCHS) vs. Comp Sales — Predictive-Power Analysis
A2: Tests whether Harvard JCHS's LIRA four-quarter moving rate of change (homeowner improvements & repairs spend) predicts HD's and LOW's actual reported US comp sales. SIMPLIFYING ASSUMPTION (per explicit user direction): LIRA's calendar-quarter labels are mapped directly to the company fiscal-quarter label of the same number -- e.g. LIRA's "2027-Q2" is treated as corresponding to "Q2 FY2027" for both HD and LOW -- even though the two periods don't actually share identical start/end dates (HD's and LOW's fiscal quarters run roughly one month behind the calendar quarter of the same number). This trades precision for simplicity; see LIRA_Remodeling_Activity.xlsx for LIRA's own calendar-quarter dating. LIRA has only 12 historical quarters (2023-Q3 through 2026-Q2) before turning into Harvard's own projections -- much less than the 25-30 quarters used for the six-macro-series analysis -- so correlation N here is small and results should be read as directional, not as statistically robust. LIRA's 4 projected quarters (2026-Q3 through 2027-Q2) map directly onto the exact 4 quarters HD and LOW need forecasted -- unlike every other series in this workbook, LIRA hands us actual forward-looking values for the full forecast horizon rather than requiring extrapolation. Comp Sales % (US) pulled from HD_LOW_Comp_Sales.xlsx as of 2026-08-20.
A4: LIRA Quarter | B4: Mapped Fiscal Quarter | C4: Period Type | D4: LIRA 4-Qtr Total ($B) | E4: LIRA 4-Qtr YoY Rate of Change | F4: HD Comp % (US) | G4: LOW Comp % (US)
A5: 2023-Q3 | B5: Q3 FY2023 | C5: Historical | D5: 511 | E5: 0.044 | F5: -0.035 | G5: -0.074
A6: 2023-Q4 | B6: Q4 FY2023 | C6: Historical | D6: 510 | E6: -0.01 | F6: -0.04 | G6: -0.062
A7: 2024-Q1 | B7: Q1 FY2024 | C7: Historical | D7: 511 | E7: -0.006 | F7: -0.032 | G7: -0.041
A8: 2024-Q2 | B8: Q2 FY2024 | C8: Historical | D8: 501 | E8: -0.023 | F8: -0.036 | G8: -0.051
A9: 2024-Q3 | B9: Q3 FY2024 | C9: Historical | D9: 498 | E9: -0.025 | F9: -0.012 | G9: -0.011
A10: 2024-Q4 | B10: Q4 FY2024 | C10: Historical | D10: 500 | E10: -0.019 | F10: 0.013 | G10: 0.002
A11: 2025-Q1 | B11: Q1 FY2025 | C11: Historical | D11: 511 | E11: -0.001 | F11: 0.002 | G11: -0.017
A12: 2025-Q2 | B12: Q2 FY2025 | C12: Historical | D12: 507 | E12: 0.012 | F12: 0.014 | G12: 0.011
A13: 2025-Q3 | B13: Q3 FY2025 | C13: Historical | D13: 506 | E13: 0.016 | F13: 0.001 | G13: 0.004
A14: 2025-Q4 | B14: Q4 FY2025 | C14: Historical | D14: 510 | E14: 0.018 | F14: 0.003 | G14: 0.013
A15: 2026-Q1 | B15: Q1 FY2026 | C15: Historical | D15: 520 | E15: 0.019 | F15: 0.004 | G15: 0.006
A16: 2026-Q2 | B16: Q2 FY2026 | C16: Historical | D16: 517 | E16: 0.02 | F16: 0.013 | G16: 0.002
A17: 2026-Q3 | B17: Q3 FY2026 | C17: Projected | D17: 517 | E17: 0.021
A18: 2026-Q4 | B18: Q4 FY2026 | C18: Projected | D18: 520 | E18: 0.021
A19: 2027-Q1 | B19: Q1 FY2027 | C19: Projected | D19: 524 | E19: 0.007
A20: 2027-Q2 | B20: Q2 FY2027 | C20: Projected | D20: 519 | E20: 0.005
A22: Amber italic rows are LIRA's own forward-looking projections (2026-Q3 through 2027-Q2, mapped to Q3 FY2026 - Q2 FY2027) -- no actual comp sales exist yet for these rows since HD and LOW haven't reported them.
A24: Correlation Summary (Pearson r)
A25: Contemporaneous = LIRA's YoY rate of change vs. same-mapped-quarter comp. "LIRA Leads NQ" = this quarter's LIRA reading vs. the comp N quarters ahead. N (quarter count) is shown since it's much smaller than the six-macro-series analysis -- treat r values computed on N<8 with real caution.
A27: Company | B27: Contemporaneous r | C27: Leads 1Q r | D27: Leads 2Q r | E27: Leads 3Q r | F27: N (Contemp.)
A28: HD | B28: =IFERROR(CORREL(E5:E16,F5:F16),"n/a") -> 0.18270146 | C28: =IFERROR(CORREL(E5:E15,F6:F16),"n/a") -> -0.17908647 | D28: =IFERROR(CORREL(E5:E14,F7:F16),"n/a") -> -0.34852809 | E28: =IFERROR(CORREL(E5:E13,F8:F16),"n/a") -> -0.60309273 | F28: =COUNT(F5:F16) -> 12
A29: LOW | B29: =IFERROR(CORREL(E5:E16,G5:G16),"n/a") -> 0.061394834 | C29: =IFERROR(CORREL(E5:E15,G6:G16),"n/a") -> -0.13504804 | D29: =IFERROR(CORREL(E5:E14,G7:G16),"n/a") -> -0.16704725 | E29: =IFERROR(CORREL(E5:E13,G8:G16),"n/a") -> -0.58287727 | F29: =COUNT(G5:G16) -> 12
A31: Key Takeaways
A32: • The correlation is weak at the contemporaneous horizon (HD r=0.18, LOW r=0.06) and turns increasingly NEGATIVE at longer leads (HD -0.60, LOW -0.58 at 3Q) -- the opposite of what we'd hope from the single most conceptually on-topic series in this project. Given N drops to just 9 pairs by the 3Q-lead test, these later figures are especially unstable and should not be read as a reliable trend reversal.
A33: • A few plausible explanations, none of which we can fully rule out with 12 data points: LIRA is a national, all-homeowner remodeling index (much broader than HD/LOW's specific mix of Pro, DIY, and non-remodel categories like appliances); its figures are 4-quarter MOVING totals, which smooths out the quarter-to-quarter variation that actually drives comp-sales swings; and the simplified calendar-to-fiscal-quarter label mapping used here (per user direction) introduces up to a 1-month misalignment that could blur an otherwise real relationship.
A34: • Practical implication for the forecasting model: LIRA should NOT be weighted as a strong regression predictor based on this historical correlation -- it doesn't earn that weight on the evidence. Its real value is different: it's the only series in this project that hands us actual forward-looking figures for the exact 4 quarters we need to forecast, so it's better used as a qualitative/directional cross-check on our forecast's shape (LIRA projects continued modest deceleration through 2027-Q1/Q2) rather than as an input we lean on quantitatively.

Sheet NAICS444 vs Comp Correlation
A1: NAICS 444 Retail Sales vs. Comp Sales — Correlation Analysis
A2: Tests whether public Census NAICS 444 (Building Material & Garden retail) sales growth predicts HD's and LOW's own reported US comp sales. Uses live CORREL() formulas against this workbook's own 'Quarterly Data' tab (column M = NAICS444 Y/Y growth, column L = Comp Sales % US); blank pairs (no prior-year comparison for the first 4 quarters, or the most recent quarter pending Census reporting) are automatically excluded by CORREL(). Two cuts are shown: the full sample, and a post-pandemic cut starting Q1 FY2022 (the same training window used for the Point Estimates regressions), since the 2020-2021 pandemic demand shock inflates the full-sample correlation for both names.
A4: Correlation Summary (Pearson r)
A5: Contemporaneous = retail growth vs. same-quarter comp. "Retail Leads 1Q" = this quarter's retail growth vs. NEXT quarter's comp (the predictive/forecasting use case). "Retail Lags 1Q" = this quarter's retail growth vs. the PRIOR quarter's comp.
A7: Company | B7: Sample | C7: N (Contemp.) | D7: Contemporaneous r | E7: Retail Leads 1Q r | F7: Retail Lags 1Q r
A8: HD | B8: Full sample | C8: =COUNT('Quarterly Data'!M5:M34) -> 25 | D8: =IFERROR(CORREL('Quarterly Data'!L5:L34,'Quarterly Data'!M5:M34),"n/a") -> 0.92683714 | E8: =IFERROR(CORREL('Quarterly Data'!L6:L34,'Quarterly Data'!M5:M33),"n/a") -> 0.6105798 | F8: =IFERROR(CORREL('Quarterly Data'!L5:L33,'Quarterly Data'!M6:M34),"n/a") -> 0.78697105
A9: HD | B9: Post-pandemic (Q1 FY2022 onward) | C9: =COUNT('Quarterly Data'!M17:M34) -> 17 | D9: =IFERROR(CORREL('Quarterly Data'!L17:L34,'Quarterly Data'!M17:M34),"n/a") -> 0.85626049 | E9: =IFERROR(CORREL('Quarterly Data'!L18:L34,'Quarterly Data'!M17:M33),"n/a") -> 0.59242767 | F9: =IFERROR(CORREL('Quarterly Data'!L17:L33,'Quarterly Data'!M18:M34),"n/a") -> 0.6492782
A11: LOW | B11: Full sample | C11: =COUNT('Quarterly Data'!M39:M68) -> 25 | D11: =IFERROR(CORREL('Quarterly Data'!L39:L68,'Quarterly Data'!M39:M68),"n/a") -> 0.82417261 | E11: =IFERROR(CORREL('Quarterly Data'!L40:L68,'Quarterly Data'!M39:M67),"n/a") -> 0.47726697 | F11: =IFERROR(CORREL('Quarterly Data'!L39:L67,'Quarterly Data'!M40:M68),"n/a") -> 0.79072824
A12: LOW | B12: Post-pandemic (Q1 FY2022 onward) | C12: =COUNT('Quarterly Data'!M51:M68) -> 17 | D12: =IFERROR(CORREL('Quarterly Data'!L51:L68,'Quarterly Data'!M51:M68),"n/a") -> 0.6288473 | E12: =IFERROR(CORREL('Quarterly Data'!L52:L68,'Quarterly Data'!M51:M67),"n/a") -> 0.53113608 | F12: =IFERROR(CORREL('Quarterly Data'!L51:L67,'Quarterly Data'!M52:M68),"n/a") -> 0.33940674
A15: Key Takeaways
A16: • For both names, the contemporaneous (same-quarter) relationship is the strongest of the three tested -- retail sales data and comp sales move together in the same period more than either leads or lags the other, consistent with the earlier version of this analysis (full-sample HD r~0.93, LOW r~0.82).
A17: • HD's correlation with NAICS444 retail sales is consistently stronger and more robust than LOW's, and holds up noticeably better in the post-pandemic cut -- LOW's full-sample correlation is more inflated by the shared 2020-2021 demand shock than HD's.
A18: • Retail data one quarter ahead ("Retail Leads 1Q") is a meaningfully weaker predictor than the same-quarter relationship for both names, reinforcing that NAICS444 works better as a same-quarter nowcast/cross-check than as a forward-looking predictor -- consistent with why it isn't used as a regression input in the Point Estimates tab (Census also reports it with a lag, so it isn't fully available for the most recent quarter anyway).
A19: • Practical implication: NAICS444 is a useful SAME-QUARTER sanity check on comp sales once both are reported (helpful for validating the underlying macro backdrop), but its 1-quarter-lead relationship isn't strong enough on its own to replace the mortgage-rate/consumer-sentiment regressions used for the forward point estimates.

Sheet Point Estimates
A1: Point Estimate Build — HD & LOW, Q3 FY2026 – Q2 FY2027
A2: Point Estimate = 0.85 x (Baseline + Macro Adjustment) + 0.15 x LIRA's own forward-looking projection. Baseline = trailing 2-quarter average of the company's own actual comp sales (anchors to recent momentum). Macro Adjustment = regression slope x (projected predictor - the predictor's own trailing 4-quarter average) -- measures deviation from the predictor's RECENT normal, not the full training-period average, so one volatile reading can't be fully extrapolated at face value. Near-term quarters use mortgage rate (projected as a 50/50 blend of the latest reading and its trailing average); far-out quarters use consumer sentiment (projected by carrying its recent trailing-4-quarter drift rate forward, tapered 19%/quarter rather than held flat indefinitely). Regression trained on Q1 FY2022-present throughout (excludes the pandemic-distorted 2019-2021 period). Full narrative rationale on the Overview tab.
A4: HD Regressions
A5: Recent Performance Baseline (trailing 2Q avg comp sales) | B5: =AVERAGE('Quarterly Data'!L33:L34) -> 0.0085
A7: Q3 FY2026 (1 quarter ahead) — Mortgage Rate, Leads 1Q
A8: Predictor (X) | B8: 30-Yr Mortgage Rate (%)
A9: N (historical pairs, FY2022+) | B9: =COUNT('Quarterly Data'!E17:E33) -> 17
A10: Slope (raw) | B10: =SLOPE('Quarterly Data'!L18:L34,'Quarterly Data'!E17:E33) -> -0.031486994
A11: Intercept | B11: =INTERCEPT('Quarterly Data'!L18:L34,'Quarterly Data'!E17:E33) -> 0.19722498
A12: R (correlation) | B12: =CORREL('Quarterly Data'!L18:L34,'Quarterly Data'!E17:E33) -> -0.7715073
A13: Latest reading (most recent actual quarter) | B13: ='Quarterly Data'!E34 -> 6.4953846
A14: Trailing 4Q average (recent normal) | B14: =AVERAGE('Quarterly Data'!E31:E34) -> 6.3142308
A15: Projected predictor (50/50 blend of latest + trailing avg) | B15: =(B13+B14)/2 -> 6.4048077
A16: Predictor deviation from recent normal (projected - trailing avg) | B16: =B15-B14 -> 0.090576923
A17: Macro Adjustment (slope x deviation) | B17: =B10*B16 -> -0.002851995
A18: Regression Component (Baseline + Macro Adjustment) | B18: =B5+B17 -> 0.005648005
A19: LIRA Projection (this quarter, from LIRA vs Comp Correlation tab) | B19: ='LIRA vs Comp Correlation'!E17 -> 0.021
A20: Point Estimate — Q3 FY2026 (=85% regression / 15% LIRA) | B20: =(1-0.15)*B18+0.15*B19 -> 0.0079508042
A22: Q4 FY2026 (2 quarters ahead) — Mortgage Rate, Leads 2Q
A23: Predictor (X) | B23: 30-Yr Mortgage Rate (%)
A24: N (historical pairs, FY2022+) | B24: =COUNT('Quarterly Data'!E17:E32) -> 16
A25: Slope (raw) | B25: =SLOPE('Quarterly Data'!L19:L34,'Quarterly Data'!E17:E32) -> -0.016815779
A26: Intercept | B26: =INTERCEPT('Quarterly Data'!L19:L34,'Quarterly Data'!E17:E32) -> 0.099839999
A27: R (correlation) | B27: =CORREL('Quarterly Data'!L19:L34,'Quarterly Data'!E17:E32) -> -0.48386334
A28: Latest reading (most recent actual quarter) | B28: ='Quarterly Data'!E34 -> 6.4953846
A29: Trailing 4Q average (recent normal) | B29: =AVERAGE('Quarterly Data'!E31:E34) -> 6.3142308
A30: Projected predictor (50/50 blend of latest + trailing avg) | B30: =(B28+B29)/2 -> 6.4048077
A31: Predictor deviation from recent normal (projected - trailing avg) | B31: =B30-B29 -> 0.090576923
A32: Macro Adjustment (slope x deviation) | B32: =B25*B31 -> -0.0015231215
A33: Regression Component (Baseline + Macro Adjustment) | B33: =B5+B32 -> 0.0069768785
A34: LIRA Projection (this quarter, from LIRA vs Comp Correlation tab) | B34: ='LIRA vs Comp Correlation'!E18 -> 0.021
A35: Point Estimate — Q4 FY2026 (=85% regression / 15% LIRA) | B35: =(1-0.15)*B33+0.15*B34 -> 0.0090803467
A37: Q1 FY2027 (4 quarters ahead) — Consumer Sentiment, Leads 4Q
A38: Predictor (X) | B38: Consumer Sentiment
A39: N (historical pairs, FY2022+) | B39: =COUNT('Quarterly Data'!I17:I30) -> 14
A40: Slope (raw) | B40: =SLOPE('Quarterly Data'!L21:L34,'Quarterly Data'!I17:I30) -> 0.0012661831
A41: Intercept | B41: =INTERCEPT('Quarterly Data'!L21:L34,'Quarterly Data'!I17:I30) -> -0.093998019
A42: R (correlation) | B42: =CORREL('Quarterly Data'!L21:L34,'Quarterly Data'!I17:I30) -> 0.38349463
A43: Latest reading (Q1 FY2026, most recent complete quarter) | B43: ='Quarterly Data'!I33 -> 52.845055
A44: Trailing 4Q avg rate of change (drift/quarter) | B44: =(B43-'Quarterly Data'!I29)/4 -> -1.1403846
A45: Trailing 4Q average (recent normal) | B45: =AVERAGE('Quarterly Data'!I30:I33) -> 55.070604
A46: Taper decay factor / quarters extrapolated (lead) | B46: 0.8 decay, 4Q lead
A47: Cumulative taper multiplier (=(1-decay^lead)/(1-decay)) | B47: =(1-0.8^4)/(1-0.8) -> 2.952
A48: Projected predictor (tapered drift extrapolation) | B48: =B43+B44*B47 -> 49.47864
A49: Predictor deviation from recent normal (projected - trailing avg) | B49: =B48-B45 -> -5.5919648
A50: Macro Adjustment (slope x deviation) | B50: =B40*B49 -> -0.0070804511
A51: Regression Component (Baseline + Macro Adjustment) | B51: =B5+B50 -> 0.0014195489
A52: LIRA Projection (this quarter, from LIRA vs Comp Correlation tab) | B52: ='LIRA vs Comp Correlation'!E19 -> 0.007
A53: Point Estimate — Q1 FY2027 (=85% regression / 15% LIRA) | B53: =(1-0.15)*B51+0.15*B52 -> 0.0022566165
A55: Q2 FY2027 (5 quarters ahead) — Consumer Sentiment, Leads 5Q
A56: Predictor (X) | B56: Consumer Sentiment
A57: N (historical pairs, FY2022+) | B57: =COUNT('Quarterly Data'!I17:I29) -> 13
A58: Slope (raw) | B58: =SLOPE('Quarterly Data'!L22:L34,'Quarterly Data'!I17:I29) -> 0.0019768396
A59: Intercept | B59: =INTERCEPT('Quarterly Data'!L22:L34,'Quarterly Data'!I17:I29) -> -0.13823685
A60: R (correlation) | B60: =CORREL('Quarterly Data'!L22:L34,'Quarterly Data'!I17:I29) -> 0.6435584
A61: Latest reading (Q1 FY2026, most recent complete quarter) | B61: ='Quarterly Data'!I33 -> 52.845055
A62: Trailing 4Q avg rate of change (drift/quarter) | B62: =(B61-'Quarterly Data'!I29)/4 -> -1.1403846
A63: Trailing 4Q average (recent normal) | B63: =AVERAGE('Quarterly Data'!I30:I33) -> 55.070604
A64: Taper decay factor / quarters extrapolated (lead) | B64: 0.8 decay, 5Q lead
A65: Cumulative taper multiplier (=(1-decay^lead)/(1-decay)) | B65: =(1-0.8^5)/(1-0.8) -> 3.3616
A66: Projected predictor (tapered drift extrapolation) | B66: =B61+B62*B65 -> 49.011538
A67: Slope cap (max 1.75x the Leads-4Q slope) | B67: =1.75*ABS(B40) -> 0.0022158203
A68: Slope (capped) | B68: =SIGN(B58)*MIN(ABS(B58),B67) -> 0.0019768396
A69: Predictor deviation from recent normal (projected - trailing avg) | B69: =B66-B63 -> -6.0590664
A70: Macro Adjustment (slope x deviation) | B70: =B68*B69 -> -0.011977802
A71: Regression Component (Baseline + Macro Adjustment) | B71: =B5+B70 -> -0.0034778024
A72: LIRA Projection (this quarter, from LIRA vs Comp Correlation tab) | B72: ='LIRA vs Comp Correlation'!E20 -> 0.005
A73: Point Estimate — Q2 FY2027 (=85% regression / 15% LIRA) | B73: =(1-0.15)*B71+0.15*B72 -> -0.0022061321
A76: LOW Regressions
A77: Recent Performance Baseline (trailing 2Q avg comp sales) | B77: =AVERAGE('Quarterly Data'!L67:L68) -> 0.004
A79: Q3 FY2026 (1 quarter ahead) — Mortgage Rate, Leads 1Q
A80: Predictor (X) | B80: 30-Yr Mortgage Rate (%)
A81: N (historical pairs, FY2022+) | B81: =COUNT('Quarterly Data'!E51:E67) -> 17
A82: Slope (raw) | B82: =SLOPE('Quarterly Data'!L52:L68,'Quarterly Data'!E51:E67) -> -0.021704772
A83: Intercept | B83: =INTERCEPT('Quarterly Data'!L52:L68,'Quarterly Data'!E51:E67) -> 0.12420739
A84: R (correlation) | B84: =CORREL('Quarterly Data'!L52:L68,'Quarterly Data'!E51:E67) -> -0.51987511
A85: Latest reading (most recent actual quarter) | B85: ='Quarterly Data'!E68 -> 6.4953846
A86: Trailing 4Q average (recent normal) | B86: =AVERAGE('Quarterly Data'!E65:E68) -> 6.3142308
A87: Projected predictor (50/50 blend of latest + trailing avg) | B87: =(B85+B86)/2 -> 6.4048077
A88: Predictor deviation from recent normal (projected - trailing avg) | B88: =B87-B86 -> 0.090576923
A89: Macro Adjustment (slope x deviation) | B89: =B82*B88 -> -0.0019659514
A90: Regression Component (Baseline + Macro Adjustment) | B90: =B77+B89 -> 0.0020340486
A91: LIRA Projection (this quarter, from LIRA vs Comp Correlation tab) | B91: ='LIRA vs Comp Correlation'!E17 -> 0.021
A92: Point Estimate — Q3 FY2026 (=85% regression / 15% LIRA) | B92: =(1-0.15)*B90+0.15*B91 -> 0.0048789413
A94: Q4 FY2026 (2 quarters ahead) — Mortgage Rate, Leads 2Q
A95: Predictor (X) | B95: 30-Yr Mortgage Rate (%)
A96: N (historical pairs, FY2022+) | B96: =COUNT('Quarterly Data'!E51:E66) -> 16
A97: Slope (raw) | B97: =SLOPE('Quarterly Data'!L53:L68,'Quarterly Data'!E51:E66) -> -0.014948342
A98: Intercept | B98: =INTERCEPT('Quarterly Data'!L53:L68,'Quarterly Data'!E51:E66) -> 0.080072206
A99: R (correlation) | B99: =CORREL('Quarterly Data'!L53:L68,'Quarterly Data'!E51:E66) -> -0.36097662
A100: Latest reading (most recent actual quarter) | B100: ='Quarterly Data'!E68 -> 6.4953846
A101: Trailing 4Q average (recent normal) | B101: =AVERAGE('Quarterly Data'!E65:E68) -> 6.3142308
A102: Projected predictor (50/50 blend of latest + trailing avg) | B102: =(B100+B101)/2 -> 6.4048077
A103: Predictor deviation from recent normal (projected - trailing avg) | B103: =B102-B101 -> 0.090576923
A104: Macro Adjustment (slope x deviation) | B104: =B97*B103 -> -0.0013539748
A105: Regression Component (Baseline + Macro Adjustment) | B105: =B77+B104 -> 0.0026460252
A106: LIRA Projection (this quarter, from LIRA vs Comp Correlation tab) | B106: ='LIRA vs Comp Correlation'!E18 -> 0.021
A107: Point Estimate — Q4 FY2026 (=85% regression / 15% LIRA) | B107: =(1-0.15)*B105+0.15*B106 -> 0.0053991214
A109: Q1 FY2027 (4 quarters ahead) — Consumer Sentiment, Leads 4Q
A110: Predictor (X) | B110: Consumer Sentiment
...

Sheet Macro vs Comp Correlation
A1: Macro Indicators vs. Comp Sales — Predictive-Power Analysis
A2: Tests whether the six macro series in this workbook (Mortgage Rate, Existing Home Sales, New Home Sales, CPI-U, U. Michigan Consumer Sentiment, Building Permits) predict HD's and LOW's actual reported US comp sales -- same approach as the NAICS444 retail-sales analysis in HD_LOW_Comp_Sales.xlsx's Analysis tab, applied here to the macro series instead. Comp Sales % (US) values are pulled from HD_LOW_Comp_Sales.xlsx as of 2026-08-20 (see per-cell comments for exact source row); the six macro columns are live formula references to this workbook's Quarterly Data tab. Correlation Summary below computes Pearson r via live CORREL() formulas for six lag structures per series per company: Contemporaneous (same quarter) plus Macro Leads 1Q through 5Q (this quarter's macro reading vs. the comp N quarters ahead -- the directly forecast-usable relationships, since these series don't carry NAICS444's multi-quarter reporting lag; extended one quarter beyond this assignment's 4-quarter forecast horizon as an extra check on how quickly each series' predictive power ultimately decays). CORREL() automatically excludes pairs where either value is blank, so trailing quarters where a series hasn't caught up to the fiscal-quarter-end yet are handled correctly without excluding the whole row.
A4: Home Depot (HD)
A5: Fiscal Quarter | B5: Comp Sales % (US) | C5: Mortgage Rate (%) | D5: Existing Home Sales (M, SAAR) | E5: New Home Sales (M, SAAR) | F5: CPI-U Y/Y Growth (%) | G5: Consumer Sentiment | H5: Building Permits (M Units)
A6: Q1 FY2019 | B6: 0.03 | C6: ='Quarterly Data'!E5 -> 4.25 | D6: ='Quarterly Data'!F5 -> 5.292967 | E6: ='Quarterly Data'!G5 -> 0.68804608 | F6: ='Quarterly Data'!H5 -> 0.017974246 | G6: ='Quarterly Data'!I5 -> 96.828571 | H6: ='Quarterly Data'!J5 -> 1.3042857
A7: Q2 FY2019 | B7: 0.031 | C7: ='Quarterly Data'!E6 -> 3.8646154 | D7: ='Quarterly Data'!F6 -> 5.3507692 | E7: ='Quarterly Data'!G6 -> 0.66898454 | F7: ='Quarterly Data'!H6 -> 0.017464619 | G7: ='Quarterly Data'!I6 -> 98.413187 | H7: ='Quarterly Data'!J6 -> 1.348011
A8: Q3 FY2019 | B8: 0.038 | C8: ='Quarterly Data'!E7 -> 3.63 | D8: ='Quarterly Data'!F7 -> 5.4389011 | E8: ='Quarterly Data'!G7 -> 0.71534397 | F8: ='Quarterly Data'!H7 -> 0.017523647 | G8: ='Quarterly Data'!I7 -> 93.093407 | H8: ='Quarterly Data'!J7 -> 1.4934286
A9: Q4 FY2019 | B9: 0.053 | C9: ='Quarterly Data'!E8 -> 3.6753846 | D9: ='Quarterly Data'!F8 -> 5.4614286 | E9: ='Quarterly Data'!G8 -> 0.70004951 | F9: ='Quarterly Data'!H8 -> 0.022820804 | G9: ='Quarterly Data'!I8 -> 98.765934 | H9: ='Quarterly Data'!J8 -> 1.4867033
A10: Q1 FY2020 | B10: 0.075 | C10: ='Quarterly Data'!E9 -> 3.3992308 | D10: ='Quarterly Data'!F9 -> 5.0636264 | E10: ='Quarterly Data'!G9 -> 0.63634266 | F10: ='Quarterly Data'!H9 -> 0.012967844 | G10: ='Quarterly Data'!I9 -> 86.373626 | H10: ='Quarterly Data'!J9 -> 1.2906703
A11: Q2 FY2020 | B11: 0.25 | C11: ='Quarterly Data'!E10 -> 3.1276923 | D11: ='Quarterly Data'!F10 -> 4.8872527 | E11: ='Quarterly Data'!G10 -> 0.87110461 | F11: ='Quarterly Data'!H10 -> 0.0061011169 | G11: ='Quarterly Data'!I10 -> 74.31978 | H11: ='Quarterly Data'!J10 -> 1.3823626
A12: Q3 FY2020 | B12: 0.246 | C12: ='Quarterly Data'!E11 -> 2.8823077 | D12: ='Quarterly Data'!F11 -> 6.4751648 | E12: ='Quarterly Data'!G11 -> 1.0071598 | F12: ='Quarterly Data'!H11 -> 0.012793131 | G12: ='Quarterly Data'!I11 -> 78.830769 | H12: ='Quarterly Data'!J11 -> 1.6005495
A13: Q4 FY2020 | B13: 0.25 | C13: ='Quarterly Data'!E12 -> 2.7246154 | D13: ='Quarterly Data'!F12 -> 6.7138462 | E13: ='Quarterly Data'!G12 -> 0.883299 | F13: ='Quarterly Data'!H12 -> 0.013024825 | G13: ='Quarterly Data'!I12 -> 78.90989 | H13: ='Quarterly Data'!J12 -> 1.7693297
A14: Q1 FY2021 | B14: 0.299 | C14: ='Quarterly Data'!E13 -> 2.99 | D14: ='Quarterly Data'!F13 -> 6.0172527 | E14: ='Quarterly Data'!G13 -> 0.81287482 | F14: ='Quarterly Data'!H13 -> 0.028953556 | G14: ='Quarterly Data'!I13 -> 83.484615 | H14: ='Quarterly Data'!J13 -> 1.7234066
A15: Q2 FY2021 | B15: 0.034 | C15: ='Quarterly Data'!E14 -> 2.93 | D15: ='Quarterly Data'!F14 -> 5.8853846 | E15: ='Quarterly Data'!G14 -> 0.72516632 | F15: ='Quarterly Data'!H14 -> 0.052388271 | G15: ='Quarterly Data'!I14 -> 83.03956 | H15: ='Quarterly Data'!J14 -> 1.6779231
A16: Q3 FY2021 | B16: 0.055 | C16: ='Quarterly Data'!E15 -> 2.9338462 | D16: ='Quarterly Data'!F15 -> 6.1718681 | E16: ='Quarterly Data'!G15 -> 0.70319032 | F16: ='Quarterly Data'!H15 -> 0.056266336 | G16: ='Quarterly Data'!I15 -> 71.601099 | H16: ='Quarterly Data'!J15 -> 1.696033
A17: Q4 FY2021 | B17: 0.076 | C17: ='Quarterly Data'!E16 -> 3.1953846 | D17: ='Quarterly Data'!F16 -> 6.3778022 | E17: ='Quarterly Data'!G16 -> 0.80247313 | F17: ='Quarterly Data'!H16 -> 0.071021417 | G17: ='Quarterly Data'!I16 -> 68.424176 | H17: ='Quarterly Data'!J16 -> 1.859956
... A35: Q2 FY2026 | B35: 0.013 | C35: ='Quarterly Data'!E34 -> 6.4953846 | D35: ='Quarterly Data'!F34 -> 0 | E35: ='Quarterly Data'!G34 -> 0 | F35: ='Quarterly Data'!H34 -> 0.036781701 | G35: ='Quarterly Data'!I34 -> 0 | H35: ='Quarterly Data'!J34 -> 0
A37: Lowe's (LOW)
A38: Fiscal Quarter | B38: Comp Sales % (US) | C38: Mortgage Rate (%) | D38: Existing Home Sales (M, SAAR) | E38: New Home Sales (M, SAAR) | F38: CPI-U Y/Y Growth (%) | G38: Consumer Sentiment | H38: Building Permits (M Units)
A39: Q1 FY2019 | B39: 0.042 | C39: ='Quarterly Data'!E39 -> 4.25 | D39: ='Quarterly Data'!F39 -> 5.2967033 | E39: ='Quarterly Data'!G39 -> 0.68869469 | F39: ='Quarterly Data'!H39 -> 0.017915096 | G39: ='Quarterly Data'!I39 -> 96.692308 | H39: ='Quarterly Data'!J39 -> 1.3029451
A40: Q2 FY2019 | B40: 0.032 | C40: ='Quarterly Data'!E40 -> 3.8646154 | D40: ='Quarterly Data'!F40 -> 5.3474725 | E40: ='Quarterly Data'!G40 -> 0.66692864 | F40: ='Quarterly Data'!H40 -> 0.017473497 | G40: ='Quarterly Data'!I40 -> 98.637363 | H40: ='Quarterly Data'!J40 -> 1.345044
A41: Q3 FY2019 | B41: 0.03 | C41: ='Quarterly Data'!E41 -> 3.63 | D41: ='Quarterly Data'!F41 -> 5.441978 | E41: ='Quarterly Data'!G41 -> 0.71532572 | F41: ='Quarterly Data'!H41 -> 0.017457502 | G41: ='Quarterly Data'!I41 -> 92.93956 | H41: ='Quarterly Data'!J41 -> 1.4922637
A42: Q4 FY2019 | B42: 0.026 | C42: ='Quarterly Data'!E42 -> 3.6753846 | D42: ='Quarterly Data'!F42 -> 5.4521978 | E42: ='Quarterly Data'!G42 -> 0.70016789 | F42: ='Quarterly Data'!H42 -> 0.022758348 | G42: ='Quarterly Data'!I42 -> 98.673626 | H42: ='Quarterly Data'!J42 -> 1.4883297
A43: Q1 FY2020 | B43: 0.123 | C43: ='Quarterly Data'!E43 -> 3.3992308 | D43: ='Quarterly Data'!F43 -> 5.1045055 | E43: ='Quarterly Data'!G43 -> 0.63634311 | F43: ='Quarterly Data'!H43 -> 0.013455572 | G43: ='Quarterly Data'!I43 -> 87.004396 | H43: ='Quarterly Data'!J43 -> 1.2952857
A44: Q2 FY2020 | B44: 0.351 | C44: ='Quarterly Data'!E44 -> 3.1276923 | D44: ='Quarterly Data'!F44 -> 4.8413187 | E44: ='Quarterly Data'!G44 -> 0.86432457 | F44: ='Quarterly Data'!H44 -> 0.0058391155 | G44: ='Quarterly Data'!I44 -> 74.28022 | H44: ='Quarterly Data'!J44 -> 1.3761429
A45: Q3 FY2020 | B45: 0.304 | C45: ='Quarterly Data'!E45 -> 2.8823077 | D45: ='Quarterly Data'!F45 -> 6.4582418 | E45: ='Quarterly Data'!G45 -> 1.008521 | F45: ='Quarterly Data'!H45 -> 0.012816043 | G45: ='Quarterly Data'!I45 -> 78.715385 | H45: ='Quarterly Data'!J45 -> 1.597956
A46: Q4 FY2020 | B46: 0.286 | C46: ='Quarterly Data'!E46 -> 2.7246154 | D46: ='Quarterly Data'!F46 -> 6.7156044 | E46: ='Quarterly Data'!G46 -> 0.8845058 | F46: ='Quarterly Data'!H46 -> 0.013043239 | G46: ='Quarterly Data'!I46 -> 78.917582 | H46: ='Quarterly Data'!J46 -> 1.7648462
A47: Q1 FY2021 | B47: 0.244 | C47: ='Quarterly Data'!E47 -> 2.99 | D47: ='Quarterly Data'!F47 -> 6.0368132 | E47: ='Quarterly Data'!G47 -> 0.81687308 | F47: ='Quarterly Data'!H47 -> 0.028103869 | G47: ='Quarterly Data'!I47 -> 83.398901 | H47: ='Quarterly Data'!J47 -> 1.7267253
A48: Q2 FY2021 | B48: -0.022 | C48: ='Quarterly Data'!E48 -> 2.93 | D48: ='Quarterly Data'!F48 -> 5.8824176 | E48: ='Quarterly Data'!G48 -> 0.72517579 | F48: ='Quarterly Data'!H48 -> 0.052355754 | G48: ='Quarterly Data'!I48 -> 83.196703 | H48: ='Quarterly Data'!J48 -> 1.677967
A49: Q3 FY2021 | B49: 0.026 | C49: ='Quarterly Data'!E49 -> 2.9338462 | D49: ='Quarterly Data'!F49 -> 6.162967 | E49: ='Quarterly Data'!G49 -> 0.70379013 | F49: ='Quarterly Data'!H49 -> 0.056022093 | G49: ='Quarterly Data'!I49 -> 71.69011 | H49: ='Quarterly Data'!J49 -> 1.6961209
A50: Q4 FY2021 | B50: 0.051 | C50: ='Quarterly Data'!E50 -> 3.1953846 | D50: ='Quarterly Data'!F50 -> 6.3742857 | E50: ='Quarterly Data'!G50 -> 0.79983447 | F50: ='Quarterly Data'!H50 -> 0.070752108 | G50: ='Quarterly Data'!I50 -> 68.523077 | H50: ='Quarterly Data'!J50 -> 1.855033
... A68: Q2 FY2026 | B68: 0.002 | C68: ='Quarterly Data'!E68 -> 6.4953846 | D68: ='Quarterly Data'!F68 -> 4.1061538 | E68: ='Quarterly Data'!G68 -> 0 | F68: ='Quarterly Data'!H68 -> 0.037014697 | G68: ='Quarterly Data'!I68 -> 0 | H68: ='Quarterly Data'!J68 -> 1.4093736
A70: Correlation Summary (Pearson r)
A71: Contemporaneous = macro reading vs. same-quarter comp. "Macro Leads NQ" = this quarter's macro reading vs. the comp N quarters ahead (the relationship usable for an N-quarter-ahead forecast), computed out through 4 quarters to cover the full forecast horizon for this assignment. All use live CORREL() formulas over the full contiguous data range above; blank pairs (a series not yet caught up to a fiscal quarter, or the shift running past the last known quarter) are automatically excluded by CORREL().
A73: Company | B73: Macro Series | C73: Contemporaneous r | D73: Macro Leads 1Q r | E73: Macro Leads 2Q r | F73: Macro Leads 3Q r | G73: Macro Leads 4Q r | H73: Macro Leads 5Q r
A74: HD | B74: Mortgage Rate (%) | C74: =IFERROR(CORREL(C6:C35,B6:B35),"n/a") -> -0.73831236 | D74: =IFERROR(CORREL(C6:C34,B7:B35),"n/a") -> -0.72785101 | E74: =IFERROR(CORREL(C6:C33,B8:B35),"n/a") -> -0.67054583 | F74: =IFERROR(CORREL(C6:C32,B9:B35),"n/a") -> -0.6049121 | G74: =IFERROR(CORREL(C6:C31,B10:B35),"n/a") -> -0.50963476 | H74: =IFERROR(CORREL(C6:C30,B11:B35),"n/a") -> -0.39587727
A75: HD | B75: Existing Home Sales (M, SAAR) | C75: =IFERROR(CORREL(D6:D35,B6:B35),"n/a") -> 0.68968826 | D75: =IFERROR(CORREL(D6:D34,B7:B35),"n/a") -> 0.62319214 | E75: =IFERROR(CORREL(D6:D33,B8:B35),"n/a") -> 0.48695534 | F75: =IFERROR(CORREL(D6:D32,B9:B35),"n/a") -> 0.3278977 | G75: =IFERROR(CORREL(D6:D31,B10:B35),"n/a") -> 0.31396434 | H75: =IFERROR(CORREL(D6:D30,B11:B35),"n/a") -> 0.25035353
A76: HD | B76: New Home Sales (M, SAAR) | C76: =IFERROR(CORREL(E6:E35,B6:B35),"n/a") -> 0.78495671 | D76: =IFERROR(CORREL(E6:E34,B7:B35),"n/a") -> 0.66045282 | E76: =IFERROR(CORREL(E6:E33,B8:B35),"n/a") -> 0.58400063 | F76: =IFERROR(CORREL(E6:E32,B9:B35),"n/a") -> 0.30790872 | G76: =IFERROR(CORREL(E6:E31,B10:B35),"n/a") -> 0.061108414 | H76: =IFERROR(CORREL(E6:E30,B11:B35),"n/a") -> 0.12054741
A77: HD | B77: CPI-U Y/Y Growth (%) | C77: =IFERROR(CORREL(F6:F35,B6:B35),"n/a") -> -0.27724374 | D77: =IFERROR(CORREL(F6:F34,B7:B35),"n/a") -> -0.40255426 | E77: =IFERROR(CORREL(F6:F33,B8:B35),"n/a") -> -0.44374338 | F77: =IFERROR(CORREL(F6:F32,B9:B35),"n/a") -> -0.52768709 | G77: =IFERROR(CORREL(F6:F31,B10:B35),"n/a") -> -0.53456616 | H77: =IFERROR(CORREL(F6:F30,B11:B35),"n/a") -> -0.54442063
A78: HD | B78: Consumer Sentiment | C78: =IFERROR(CORREL(G6:G35,B6:B35),"n/a") -> 0.31614759 | D78: =IFERROR(CORREL(G6:G34,B7:B35),"n/a") -> 0.36547366 | E78: =IFERROR(CORREL(G6:G33,B8:B35),"n/a") -> 0.53032866 | F78: =IFERROR(CORREL(G6:G32,B9:B35),"n/a") -> 0.64028478 | G78: =IFERROR(CORREL(G6:G31,B10:B35),"n/a") -> 0.80698809 | H78: =IFERROR(CORREL(G6:G30,B11:B35),"n/a") -> 0.87825302
A79: HD | B79: Building Permits (M Units) | C79: =IFERROR(CORREL(H6:H35,B6:B35),"n/a") -> 0.3141361 | D79: =IFERROR(CORREL(H6:H34,B7:B35),"n/a") -> 0.096947762 | E79: =IFERROR(CORREL(H6:H33,B8:B35),"n/a") -> -0.11546957 | F79: =IFERROR(CORREL(H6:H32,B9:B35),"n/a") -> -0.27513425 | G79: =IFERROR(CORREL(H6:H31,B10:B35),"n/a") -> -0.38395447 | H79: =IFERROR(CORREL(H6:H30,B11:B35),"n/a") -> -0.4125487
A81: LOW | B81: Mortgage Rate (%) | C81: =IFERROR(CORREL(C39:C68,B39:B68),"n/a") -> -0.67602618 | D81: =IFERROR(CORREL(C39:C67,B40:B68),"n/a") -> -0.62279925 | E81: =IFERROR(CORREL(C39:C66,B41:B68),"n/a") -> -0.54438984 | F81: =IFERROR(CORREL(C39:C65,B42:B68),"n/a") -> -0.48601768 | G81: =IFERROR(CORREL(C39:C64,B43:B68),"n/a") -> -0.40389384 | H81: =IFERROR(CORREL(C39:C63,B44:B68),"n/a") -> -0.29634149
A82: LOW | B82: Existing Home Sales (M, SAAR) | C82: =IFERROR(CORREL(D39:D68,B39:B68),"n/a") -> 0.57343675 | D82: =IFERROR(CORREL(D39:D67,B40:B68),"n/a") -> 0.45573141 | E82: =IFERROR(CORREL(D39:D66,B41:B68),"n/a") -> 0.31835601 | F82: =IFERROR(CORREL(D39:D65,B42:B68),"n/a") -> 0.23313477 | G82: =IFERROR(CORREL(D39:D64,B43:B68),"n/a") -> 0.2507725 | H82: =IFERROR(CORREL(D39:D63,B44:B68),"n/a") -> 0.17039108
A83: LOW | B83: New Home Sales (M, SAAR) | C83: =IFERROR(CORREL(E39:E68,B39:B68),"n/a") -> 0.79668112 | D83: =IFERROR(CORREL(E39:E67,B40:B68),"n/a") -> 0.53669557 | E83: =IFERROR(CORREL(E39:E66,B41:B68),"n/a") -> 0.38539648 | F83: =IFERROR(CORREL(E39:E65,B42:B68),"n/a") -> 0.12967147 | G83: =IFERROR(CORREL(E39:E64,B43:B68),"n/a") -> -0.028862237 | H83: =IFERROR(CORREL(E39:E63,B44:B68),"n/a") -> 0.044582547
A84: LOW | B84: CPI-U Y/Y Growth (%) | C84: =IFERROR(CORREL(F39:F68,B39:B68),"n/a") -> -0.42515853 | D84: =IFERROR(CORREL(F39:F67,B40:B68),"n/a") -> -0.4600173 | E84: =IFERROR(CORREL(F39:F66,B41:B68),"n/a") -> -0.4458666 | F84: =IFERROR(CORREL(F39:F65,B42:B68),"n/a") -> -0.49267642 | G84: =IFERROR(CORREL(F39:F64,B43:B68),"n/a") -> -0.48632449 | H84: =IFERROR(CORREL(F39:F63,B44:B68),"n/a") -> -0.48251095
A85: LOW | B85: Consumer Sentiment | C85: =IFERROR(CORREL(G39:G68,B39:B68),"n/a") -> 0.30475833 | D85: =IFERROR(CORREL(G39:G67,B40:B68),"n/a") -> 0.36084697 | E85: =IFERROR(CORREL(G39:G66,B41:B68),"n/a") -> 0.52595793 | F85: =IFERROR(CORREL(G39:G65,B42:B68),"n/a") -> 0.641842 | G85: =IFERROR(CORREL(G39:G64,B43:B68),"n/a") -> 0.80044038 | H85: =IFERROR(CORREL(G39:G63,B44:B68),"n/a") -> 0.82036142
A86: LOW | B86: Building Permits (M Units) | C86: =IFERROR(CORREL(H39:H68,B39:B68),"n/a") -> 0.11079504 | D86: =IFERROR(CORREL(H39:H67,B40:B68),"n/a") -> -0.13116429 | E86: =IFERROR(CORREL(H39:H66,B41:B68),"n/a") -> -0.25465328 | F86: =IFERROR(CORREL(H39:H65,B42:B68),"n/a") -> -0.31721823 | G86: =IFERROR(CORREL(H39:H64,B43:B68),"n/a") -> -0.40221849 | H86: =IFERROR(CORREL(H39:H63,B44:B68),"n/a") -> -0.45222748
A89: Key Takeaways
A90: • New Home Sales is the single strongest macro predictor at the SHORT end of the forecast horizon (contemporaneous/1Q-lead, r~0.66-0.80 for both companies) but decays the fastest of any series -- by the 4-quarter lead it's essentially uncorrelated (HD r=0.06, LOW r=-0.03), and stays near zero at 5Q (HD 0.12, LOW 0.04). It's a strong near-term signal, not a reliable one for the back half of a 4+ quarter forecast.
A91: • Consumer Sentiment does the OPPOSITE: weak at the contemporaneous horizon (r~0.30-0.32) but strengthens steadily with every additional quarter of lead, becoming the single strongest predictor in the entire table at the 4-quarter horizon (HD r=0.81, LOW r=0.80) and continuing to strengthen even further at 5Q (HD r=0.88, LOW r=0.82) -- a striking, consistent, still-climbing pattern across both companies. This makes it the standout candidate for driving the FAR end of our forecast (Q3-Q4 out), even though it's a weak choice for the near term.
A92: • Mortgage Rate is the most 'all-around' reliable series: strongly negative at every horizon tested (roughly -0.74 to -0.40 for HD, -0.68 to -0.30 for LOW as lead extends from 0 to 5 quarters) -- it decays more gradually than New Home Sales or Building Permits, making it a solid contributor across the full forecast horizon rather than being horizon-specific, even as its strength does erode noticeably by 5Q.
A93: • CPI-U Y/Y Growth (the inflation RATE, not the index level -- an index level trends monotonically upward and isn't economically meaningful to correlate against comp sales) is moderately negative and strengthens somewhat with lead time (HD: -0.28 contemporaneous to -0.54 at 5Q; LOW: -0.43 to -0.48) -- higher inflation is associated with softer comps, a relationship that holds up reasonably well across the full horizon without being the single strongest signal at any one point.
A94: • Building Permits -- despite being the most theoretically 'leading' of the six series -- shows the weakest relationship at every horizon and gets WORSE (more negative) the further out it's tested, flipping from a modest positive at contemporaneous (HD 0.31, LOW 0.11) to clearly negative by 4-5 quarters out (HD -0.41, LOW -0.45 at 5Q) for both companies. Being a leading indicator of construction starts clearly doesn't translate into being a good leading correlate of comp sales -- the transmission timeline evidently doesn't line up with what we assumed.
A95: • Existing Home Sales sits in between: a decent contemporaneous predictor (HD 0.69, LOW 0.57) that decays steadily, ending up weak by 4-5 quarters out (HD 0.25, LOW 0.17 at 5Q) -- more durable than New Home Sales or Permits, but nowhere near as durable as Mortgage Rate or CPI-U.
A96: • Across nearly every series and lag structure, HD's correlations run modestly higher than LOW's -- consistent with the NAICS444 retail-sales finding (HD r=0.93 vs. LOW r=0.82 contemporaneous) that HD's comp sales are simply more macro-driven/predictable than LOW's, whose results carry more idiosyncratic (Pro/DIY mix, acquisition-related) variation. The one interesting exception is Consumer Sentiment, where HD and LOW stay close together at every lead (0.81 vs. 0.80 at 4Q, 0.88 vs. 0.82 at 5Q).
A97: • Bottom line for the forecasting model: no single series is reliable across the full 4-5 quarter horizon. A sensible design shifts weight from New Home Sales/Existing Home Sales (strong near-term, weak far-term) toward Consumer Sentiment (weak near-term, strongest far-term and still climbing at 5Q) as the forecast horizon extends, while treating Mortgage Rate as a steady, horizon-independent contributor and CPI-U Y/Y Growth as a moderate, gradually-strengthening secondary signal throughout, and de-emphasizing Building Permits given its weak and steadily deteriorating relationship at every tested horizon.
